logic_bank/__init__.py
logic_bank/exceptions.py
logic_bank/logic_bank.py
logic_bank/util.py
logic_bank/exec_row_logic/__init__.py
logic_bank/exec_row_logic/logic_row.py
logic_bank/exec_trans_logic/__init__.py
logic_bank/exec_trans_logic/listeners.py
logic_bank/exec_trans_logic/row_sets.py
logic_bank/extensions/__init__.py
logic_bank/extensions/allocate.py
logic_bank/extensions/copy_children.py
logic_bank/extensions/copy_row.py
logic_bank/extensions/rule_extensions.py
logic_bank/rule_bank/SingletonMeta_experiment.py
logic_bank/rule_bank/__init__.py
logic_bank/rule_bank/rule_bank.py
logic_bank/rule_bank/rule_bank_setup.py
logic_bank/rule_bank/rule_bank_withdraw.py
logic_bank/rule_type/__init__.py
logic_bank/rule_type/abstractrule.py
logic_bank/rule_type/aggregate.py
logic_bank/rule_type/constraint.py
logic_bank/rule_type/copy.py
logic_bank/rule_type/count.py
logic_bank/rule_type/derivation.py
logic_bank/rule_type/formula.py
logic_bank/rule_type/parent_cascade.py
logic_bank/rule_type/parent_check.py
logic_bank/rule_type/row_event.py
logic_bank/rule_type/sum.py
logicbank-1.30.0.dist-info/licenses/LICENSE
logicbank-1.30.0.dist-info/METADATA
logicbank-1.30.0.dist-info/WHEEL
logicbank-1.30.0.dist-info/top_level.txt
logicbank-1.30.0.dist-info/RECORD
