Metadata-Version: 2.4
Name: logicbank
Version: 1.30.0
Summary: Declare multi-table rules for SQLAlchemy update logic -- 40X more concise, Python for extensibility.
Home-page: https://github.com/valhuber/logicbank
Author: Val Huber
Author-email: Val Huber <valjhuber@gmail.com>
License: BSD
Project-URL: Homepage, https://github.com/valhuber/logicbank
Project-URL: Documentation, https://github.com/valhuber/logicbank/wiki
Project-URL: Repository, https://github.com/valhuber/logicbank
Project-URL: Issues, https://github.com/valhuber/logicbank/issues
Keywords: SQLAlchemy,business logic,rules engine,declarative,reactive
Platform: any
Classifier: Development Status :: 5 - Production/Stable
Classifier: Environment :: Web Environment
Classifier: Intended Audience :: Developers
Classifier: License :: OSI Approved :: BSD License
Classifier: Operating System :: OS Independent
Classifier: Programming Language :: Python
Classifier: Programming Language :: Python :: 3
Classifier: Programming Language :: Python :: 3.8
Classifier: Programming Language :: Python :: 3.9
Classifier: Programming Language :: Python :: 3.10
Classifier: Programming Language :: Python :: 3.11
Classifier: Programming Language :: Python :: 3.12
Classifier: Programming Language :: Python :: 3.13
Classifier: Topic :: Software Development :: Libraries :: Python Modules
Requires-Python: ~=3.8
License-File: LICENSE
Requires-Dist: python-dateutil<3,>=2.3
Requires-Dist: sqlalchemy==2.0.39
Provides-Extra: dev
Requires-Dist: pytest>=6.0; extra == "dev"
Requires-Dist: pytest-cov; extra == "dev"
Requires-Dist: black; extra == "dev"
Requires-Dist: flake8; extra == "dev"
Requires-Dist: mypy; extra == "dev"
Provides-Extra: test
Requires-Dist: pytest>=6.0; extra == "test"
Requires-Dist: pytest-cov; extra == "test"
Dynamic: author
Dynamic: home-page
Dynamic: license-file
Dynamic: platform
Dynamic: requires-python
